power_ai/common/sign.py
power_ai_common-0.0.1.dist-info/METADATA
power_ai_common-0.0.1.dist-info/WHEEL
power_ai_common-0.0.1.dist-info/RECORD
